README.md
setup.cfg
setup.py
faces/__init__.py
faces/abstract_rule.py
faces/abstract_widgets.py
faces/abstract_widgets_collection.py
faces/app.py
faces/controller.py
faces/exceptions.py
faces/observables.py
faces/utilities.py
faces/widget_creators.py
faces.egg-info/PKG-INFO
faces.egg-info/SOURCES.txt
faces.egg-info/dependency_links.txt
faces.egg-info/requires.txt
faces.egg-info/top_level.txt
faces/drawers/__init__.py
faces/drawers/drawer.py
faces/drawers/tkinter_drawer.py
faces/drawers/tkinter_screen.py