Metadata-Version: 1.1
Name: faces
Version: 0.3
Summary: A Python library for developing desktop apps in a reactive way
Home-page: https://github.com/teamfaces/faces
Author: Ricardo Gomes
Author-email: desk467@gmail.com
License: MIT
Download-URL: https://github.com/teamfaces/faces/releases/download/v0.3/faces-0.3.tar.gz
Keywords: gui,desktop-apps,mobile
Platform: UNKNOWN
Classifier: Development Status :: 3 - Alpha
Classifier: Intended Audience :: Developers
Classifier: Topic :: Software Development :: User Interfaces
Classifier: Environment :: Win32 (MS Windows)
Classifier: Environment :: X11 Applications
Classifier: License :: OSI Approved :: MIT License
Classifier: Programming Language :: Python :: 3
Classifier: Programming Language :: Python :: 3.6
